{
  "data": {
    "id": 3,
    "user": {
      "id": 3,
      "name": "\u0633\u0639\u064a\u062f",
      "email_or_phone": "saed@gmail.con"
    },
    "subtotal": 90,
    "total": 90,
    "coupon_code": null,
    "products": [
      {
        "id": 385,
        "name": "b",
        "thumbnail": "https:\/\/sadaf-group.s3.me-south-1.amazonaws.com\/products\/8271356985\/xtLykh97dsGAVO5fvTeRLCJqg13UMW2SykfNmU5D.png",
        "price": "10.00",
        "price_in_iqd": "13,300",
        "discount_price": "0",
        "discount_price_in_iqd": "0",
        "is_favorite": true,
        "quantity": 5
      },
      {
        "id": 384,
        "name": "a",
        "thumbnail": "https:\/\/sadaf-group.s3.me-south-1.amazonaws.com\/products\/5702612244\/FQ1eylETSmuyBzeVmdIVZRuf7aPMRT7QUfblVVKm.png",
        "price": "10.00",
        "price_in_iqd": "13,300",
        "discount_price": "0",
        "discount_price_in_iqd": "0",
        "is_favorite": false,
        "quantity": 4
      }
    ]
  }
}